{
  "protocolSection": {},
  "resultsSection": {
    "participantFlowModule": {},
    "baselineCharacteristicsModule": {
      "populationDescription": "Baseline data was not collected for Part 2, as no participants were enrolled in Part 2.",
      "groups": [
        {
          "id": "BG000",
          "title": "Part 1:GSK2879552 1mg QD",
          "description": "Participants received GSK2879552 1 mg orally QD in fasted condition with approximately 200 mL of water."
        },
        {
          "id": "BG001",
          "title": "Part 1: GSK2879552 2mg QD",
          "description": "Participants received GSK2879552 2 mg orally once daily in fasted condition with approximately 200 mL of water."
        }
      ],
      "denoms": [
        {
          "units": "Participants",
          "counts": [
            {
              "groupId": "BG000",
              "value": "1"
            },
            {
              "groupId": "BG001",
              "value": "2"
            }
          ]
        }
      ],
      "measures": [
        {
          "title": "Age, Continuous",
          "paramType": "MEAN",
          "dispersionType": "STANDARD_DEVIATION",
          "unitOfMeasure": "Years",
          "classes": [
            {
              "categories": [
                {
                  "measurements": [
                    {
                      "groupId": "BG000",
                      "value": "68.0",
                      "spread": "NA",
                      "comment": "Standard Deviation could not be calculated as only one participant was analyzed"
                    },
                    {
                      "groupId": "BG001",
                      "value": "73.5",
                      "spread": "2.12"
                    }
                  ]
                }
              ]
            }
          ]
        },
        {
          "title": "Sex: Female, Male",
          "paramType": "COUNT_OF_PARTICIPANTS",
          "unitOfMeasure": "Participants",
          "classes": [
            {
              "categories": [
                {
                  "title": "Female",
                  "measurements": [
                    {
                      "groupId": "BG000",
                      "value": "0"
                    },
                    {
                      "groupId": "BG001",
                      "value": "0"
                    }
                  ]
                },
                {
                  "title": "Male",
                  "measurements": [
                    {
                      "groupId": "BG000",
                      "value": "1"
                    },
                    {
                      "groupId": "BG001",
                      "value": "2"
                    }
                  ]
                }
              ]
            }
          ]
        },
        {
          "title": "Race/Ethnicity, Customized",
          "paramType": "COUNT_OF_PARTICIPANTS",
          "unitOfMeasure": "Participants",
          "classes": [
            {
              "categories": [
                {
                  "title": "Black or African American",
                  "measurements": [
                    {
                      "groupId": "BG000",
                      "value": "0"
                    },
                    {
                      "groupId": "BG001",
                      "value": "0"
                    }
                  ]
                },
                {
                  "title": "Asian - Central/South Asian Heritage",
                  "measurements": [
                    {
                      "groupId": "BG000",
                      "value": "0"
                    },
                    {
                      "groupId": "BG001",
                      "value": "0"
                    }
                  ]
                },
                {
                  "title": "Asian - East Asian Heritage",
                  "measurements": [
                    {
                      "groupId": "BG000",
                      "value": "0"
                    },
                    {
                      "groupId": "BG001",
                      "value": "0"
                    }
                  ]
                },
                {
                  "title": "Asian - South East Asian Heritage",
                  "measurements": [
                    {
                      "groupId": "BG000",
                      "value": "0"
                    },
                    {
                      "groupId": "BG001",
                      "value": "0"
                    }
                  ]
                },
                {
                  "title": "White - White/Caucasian/European Heritage",
                  "measurements": [
                    {
                      "groupId": "BG000",
                      "value": "1"
                    },
                    {
                      "groupId": "BG001",
                      "value": "2"
                    }
                  ]
                },
                {
                  "title": "Missing",
                  "measurements": [
                    {
                      "groupId": "BG000",
                      "value": "0"
                    },
                    {
                      "groupId": "BG001",
                      "value": "0"
                    }
                  ]
                }
              ]
            }
          ]
        }
      ]
    },
    "outcomeMeasuresModule": {},
    "adverseEventsModule": {},
    "moreInfoModule": {}
  },
  "documentSection": {},
  "derivedSection": {},
  "hasResults": true
}